netbox_rbac/__init__.py
netbox_rbac/api.py
netbox_rbac/apps.py
netbox_rbac/backend.py
netbox_rbac/macros.py
netbox_rbac/middleware.py
netbox_rbac/mixins.py
netbox_rbac/models.py
netbox_rbac/rule.py
netbox_rbac/urls.py
netbox_rbac/views.py
netbox_rbac/auth/__init__.py
netbox_rbac/auth/ldap.py
netbox_rbac/auth/mock.py
netbox_rbac/templates/403.html
netbox_rbac/templates/netbox_rbac/roles.html
netbox_rbac/tests/__init__.py
netbox_rbac/tests/test_macros.py
netbox_rbac/tests/test_rule.py
netbox_rbac/tests/types.py
netbox_rbac-1.0.18.dist-info/LICENSE
netbox_rbac-1.0.18.dist-info/METADATA
netbox_rbac-1.0.18.dist-info/WHEEL
netbox_rbac-1.0.18.dist-info/top_level.txt
netbox_rbac-1.0.18.dist-info/RECORD
