Metadata-Version: 2.1
Name: netbox-rbac
Version: 1.0.18
Summary: Opinionated RBAC for NetBox
Home-page: https://github.com/ebusto/netbox-rbac
Author: Eric Busto
Author-email: ebusto@nvidia.com
License: UNKNOWN
Platform: UNKNOWN
Classifier: Environment :: Web Environment
Classifier: Framework :: Django
Classifier: Intended Audience :: Developers
Classifier: License :: OSI Approved :: MIT License
Classifier: Operating System :: OS Independent
Classifier: Programming Language :: Python :: 3
License-File: LICENSE
Requires-Dist: cachetools (==4.2.4)
Requires-Dist: deepmerge (==0.3.0)
Requires-Dist: python-ldap (==3.3.1)
Requires-Dist: wcmatch (==8.2)
